MANIFEST.in
README.rst
requirements.txt
setup.cfg
setup.py
test-requirements.txt
publicdns/__init__.py
publicdns/_compat.py
publicdns/client.py
publicdns/exceptions.py
publicdns/models.py
publicdns/monkey.py
publicdns/types.py
publicdns/utils.py
publicdns.egg-info/PKG-INFO
publicdns.egg-info/SOURCES.txt
publicdns.egg-info/dependency_links.txt
publicdns.egg-info/requires.txt
publicdns.egg-info/top_level.txt