Metadata-Version: 1.1
Name: publicdns
Version: 0.1.0
Summary: UNKNOWN
Home-page: https://github.com/ssut/publicdns
Author: SuHun Han
Author-email: ssut@ssut.me
License: MIT
Platform: UNKNOWN
Classifier: Intended Audience :: Developers
Classifier: License :: OSI Approved :: MIT License
Classifier: Programming Language :: Python
Classifier: Programming Language :: Python :: 2
Classifier: Programming Language :: Python :: 3
Classifier: Topic :: Software Development :: Libraries :: Python Modules
Classifier: Operating System :: OS Independent
